{"id":23,"user_id":"100002618622831","name":"Nguyễn Dũng","profilePic":"https://scontent-dfw6-2.xx.fbcdn.net/v/t39.30808-1/607473013_25403123369358268_8765867254911955794_n.jpg?stp=cp0_dst-jpg_tt6&cstp=mx2048x2048&ctp=s50x50&_nc_cat=110&ccb=1-7&_nc_sid=1d2534&_nc_ohc=gHkCe-HYK0gQ7kNvwESYx47&_nc_oc=Adrl4C1c4eXXGRTgmOQRJbPmT-Fo__GOk4seNlczA0rRjKyh8l5MmYoW_lQ7AePTaFk&_nc_zt=24&_nc_ht=scontent-dfw6-2.xx&_nc_gid=kt1HDomaQme9Og7WZ-K4iQ&_nc_ss=72289&oh=00_AQCLyQ74O8QSRbMfRbnkTN99f-2C_j1DFrWzEMhhW_1mOg&oe=6A608469","url":"https://www.facebook.com/groups/datdonao/permalink/27720750627558797/","text":"Em đang có nhu cầu cần đặt nhiều đơn trên grab food và shopee food. \n\nCó áp mã ship, công 10K\n\nNhận đơn, đánh giá 5 sao có hình ( hình ảnh shop mình sẽ gửi cho đánh giá )\n\nCK công sau khi đánh giá\n\nIBx mình với ạ. Mình cảm ơn!","time":"2026-06-08T03:40:02.000Z"}